README.md
setup.py
haplotype_plot/__init__.py
haplotype_plot/constants.py
haplotype_plot/filter.py
haplotype_plot/genotyper.py
haplotype_plot/haplotyper.py
haplotype_plot/main.py
haplotype_plot/plot.py
haplotype_plot/reader.py
haplotype_plot/writer.py
haplotype_plot.egg-info/PKG-INFO
haplotype_plot.egg-info/SOURCES.txt
haplotype_plot.egg-info/dependency_links.txt
haplotype_plot.egg-info/entry_points.txt
haplotype_plot.egg-info/requires.txt
haplotype_plot.egg-info/top_level.txt
haplotype_plot/tests/__init__.py
haplotype_plot/tests/test_conversion.py
haplotype_plot/tests/test_genotype_selection.py
haplotype_plot/tests/test_plot.py