Metadata-Version: 2.1
Name: haplotype-plot
Version: 1.1.1
Summary: Generates haplotype plots from VCF files.
Home-page: https://github.com/neobernad/haplotype_plot
Author: José Antonio Bernabé-Díaz
Author-email: joseantonio.bernabe1@um.com
License: MIT
Platform: UNKNOWN
Classifier: Development Status :: 3 - Alpha
Classifier: Intended Audience :: Developers
Classifier: Intended Audience :: Science/Research
Classifier: Topic :: Software Development :: Build Tools
Classifier: Topic :: Scientific/Engineering
Classifier: Operating System :: Microsoft :: Windows
Classifier: Operating System :: Unix
Classifier: Operating System :: MacOS
Classifier: License :: OSI Approved :: MIT License
Classifier: Programming Language :: Python
Classifier: Programming Language :: Python :: 3.6
Requires-Python: >=3
